[
  {
    "_id": "689224b2c2d97e65ace4540b",
    "gameNameEN": "Roma",
    "gameNameCN": "罗马",
    "gameNameHK": "羅馬",
    "imageUrlEN": "https://d2bdzvbz2cmjb8.cloudfront.net/epicwin/en/110060_Roma_en.png",
    "imageUrlCN": "https://d2bdzvbz2cmjb8.cloudfront.net/epicwin/zh/110060_Roma_cn.png",
    "gameID": "40034",
    "gameType": "Slot",
    "rtpRate": "95.41%",
    "hot": false,
    "maintenance": false,
    "createdAt": "2025-10-30T08:34:54.235Z",
    "updatedAt": "2025-10-30T08:34:54.235Z",
    "__v": 0
  },
  {
    "_id": "689224b2c2d97e65ace45413",
    "gameNameEN": "White Muse",
    "gameNameCN": "白色缪斯",
    "gameNameHK": "白色繆斯",
    "imageUrlEN": "https://d2bdzvbz2cmjb8.cloudfront.net/epicwin/en/110066_WhiteMuse_en.png",
    "imageUrlCN": "https://d2bdzvbz2cmjb8.cloudfront.net/epicwin/zh/110066_WhiteMuse_cn.png",
    "gameID": "40042",
    "gameType": "Slot",
    "rtpRate": "97.13%",
    "hot": false,
    "maintenance": false,
    "createdAt": "2025-10-30T00:34:54.235Z",
    "updatedAt": "2025-10-30T00:34:54.235Z",
    "__v": 0
  },
  {
    "_id": "689224b2c2d97e65ace453f3",
    "gameNameEN": "Epic Jin Qian Wa",
    "gameNameCN": "Epic 金钱蛙",
    "gameNameHK": "Epic 金錢蛙",
    "imageUrlEN": "https://d2bdzvbz2cmjb8.cloudfront.net/epicwin/en/110037_EpicJinQianWa_en.png",
    "imageUrlCN": "https://d2bdzvbz2cmjb8.cloudfront.net/epicwin/zh/110037_EpicJinQianWa_cn.png",
    "gameID": "40010",
    "gameType": "Slot",
    "rtpRate": "97.31%",
    "hot": false,
    "maintenance": false,
    "createdAt": "2025-10-30T13:04:54.235Z",
    "updatedAt": "2025-10-30T13:04:54.235Z",
    "__v": 0
  },
  {
    "_id": "689224b2c2d97e65ace453f5",
    "gameNameEN": "Epic Great Blue",
    "gameNameCN": "Epic 海底探宝",
    "gameNameHK": "Epic 海底探寶",
    "imageUrlEN": "https://d2bdzvbz2cmjb8.cloudfront.net/epicwin/en/110039_EpicGreatBlue_en.png",
    "imageUrlCN": "https://d2bdzvbz2cmjb8.cloudfront.net/epicwin/zh/110039_EpicGreatBlue_cn.png",
    "gameID": "40012",
    "gameType": "Slot",
    "rtpRate": "96.73%",
    "hot": false,
    "maintenance": false,
    "createdAt": "2025-10-30T10:04:54.235Z",
    "updatedAt": "2025-10-30T10:04:54.235Z",
    "__v": 0
  },
  {
    "_id": "689224b2c2d97e65ace45400",
    "gameNameEN": "Winter Wonderland",
    "gameNameCN": "冬季仙境",
    "gameNameHK": "冬季仙境",
    "imageUrlEN": "https://d2bdzvbz2cmjb8.cloudfront.net/epicwin/en/110049_WinterWonderland_en.png",
    "imageUrlCN": "https://d2bdzvbz2cmjb8.cloudfront.net/epicwin/zh/110049_WinterWonderland_cn.png",
    "gameID": "40023",
    "gameType": "Slot",
    "rtpRate": "97.30%",
    "hot": false,
    "maintenance": false,
    "createdAt": "2025-10-29T20:04:54.235Z",
    "updatedAt": "2025-10-29T20:04:54.235Z",
    "__v": 0
  },
  {
    "_id": "689224b2c2d97e65ace4541d",
    "gameNameEN": "Candy Fantasy",
    "gameNameCN": "糖果奇幻旅",
    "gameNameHK": "糖果奇幻旅",
    "imageUrlEN": "https://d2bdzvbz2cmjb8.cloudfront.net/epicwin/en/Square_40052_Candy Fantasy_EN.png",
    "imageUrlCN": "https://d2bdzvbz2cmjb8.cloudfront.net/epicwin/zh/Square_40052_Candy Fantasy_CN.png",
    "gameID": "45001",
    "gameType": "Slot",
    "rtpRate": "96.00%",
    "hot": false,
    "maintenance": false,
    "createdAt": "2025-10-30T05:04:54.235Z",
    "updatedAt": "2025-10-30T05:04:54.235Z",
    "__v": 0
  },
  {
    "_id": "689224b2c2d97e65ace45402",
    "gameNameEN": "Blaze Of Fortune",
    "gameNameCN": "富火连天",
    "gameNameHK": "富火連天",
    "imageUrlEN": "https://d2bdzvbz2cmjb8.cloudfront.net/epicwin/en/110051_BlazeOfFortune_en.png",
    "imageUrlCN": "https://d2bdzvbz2cmjb8.cloudfront.net/epicwin/zh/110051_BlazeOfFortune_cn.png",
    "gameID": "40025",
    "gameType": "Slot",
    "rtpRate": "96.73%",
    "hot": true,
    "maintenance": false,
    "createdAt": "2025-10-29T23:34:54.235Z",
    "updatedAt": "2025-10-29T23:34:54.235Z",
    "__v": 0
  },
  {
    "_id": "689224b2c2d97e65ace45423",
    "gameNameEN": "Empress Glory",
    "gameNameCN": "武帝荣华",
    "gameNameHK": "武帝榮華",
    "imageUrlEN": "https://d2bdzvbz2cmjb8.cloudfront.net/epicwin/en/Empress Glory 500x500_EN.jpg",
    "imageUrlCN": "https://d2bdzvbz2cmjb8.cloudfront.net/epicwin/zh/Empress Glory 500x500_CH.jpg",
    "gameID": "45005",
    "gameType": "Slot",
    "rtpRate": "96.00%",
    "hot": false,
    "maintenance": false,
    "createdAt": "2025-10-30T11:34:54.235Z",
    "updatedAt": "2025-10-30T11:34:54.235Z",
    "__v": 0
  },
  {
    "_id": "689224b2c2d97e65ace453ef",
    "gameNameEN": "Guardians of the Galaxy 3",
    "gameNameCN": "银河护卫队3",
    "gameNameHK": "銀河守護隊3",
    "imageUrlEN": "https://d2bdzvbz2cmjb8.cloudfront.net/epicwin/en/110033_GuardiansoftheGalaxy3_en.png",
    "imageUrlCN": "https://d2bdzvbz2cmjb8.cloudfront.net/epicwin/zh/110033_GuardiansoftheGalaxy3_cn.png",
    "gameID": "40005",
    "gameType": "Slot",
    "rtpRate": "95.89%",
    "hot": false,
    "maintenance": false,
    "createdAt": "2025-10-29T08:34:54.235Z",
    "updatedAt": "2025-10-29T08:34:54.235Z",
    "__v": 0
  },
  {
    "_id": "689224b2c2d97e65ace45403",
    "gameNameEN": "Epic Music",
    "gameNameCN": "Epic 电音",
    "gameNameHK": "Epic 電音",
    "imageUrlEN": "https://d2bdzvbz2cmjb8.cloudfront.net/epicwin/en/40026_EpicMusic_en.png",
    "imageUrlCN": "https://d2bdzvbz2cmjb8.cloudfront.net/epicwin/zh/40026_EpicMusic_cn.png",
    "gameID": "40026",
    "gameType": "Slot",
    "rtpRate": "96.73%",
    "hot": false,
    "maintenance": false,
    "createdAt": "2025-10-29T11:04:54.235Z",
    "updatedAt": "2025-10-29T11:04:54.235Z",
    "__v": 0
  },
  {
    "_id": "689224b2c2d97e65ace45424",
    "gameNameEN": "Jurassic World Rebirth",
    "gameNameCN": "侏罗纪世界重生",
    "gameNameHK": "侏羅紀世界重生",
    "imageUrlEN": "https://d2bdzvbz2cmjb8.cloudfront.net/epicwin/en/SquareFlatTitle_45006_JurassicWorldRebirth.png",
    "imageUrlCN": "https://d2bdzvbz2cmjb8.cloudfront.net/epicwin/en/SquareFlatTitle_45006_JurassicWorldRebirth.png",
    "gameID": "45006",
    "gameType": "Slot",
    "rtpRate": "96.00%",
    "hot": false,
    "maintenance": false,
    "createdAt": "2025-10-30T09:04:54.235Z",
    "updatedAt": "2025-10-30T09:04:54.235Z",
    "__v": 0
  },
  {
    "_id": "689224b2c2d97e65ace45415",
    "gameNameEN": "Stone Saga",
    "gameNameCN": "石文传奇",
    "gameNameHK": "石文傳奇",
    "imageUrlEN": "https://d2bdzvbz2cmjb8.cloudfront.net/epicwin/en/40047_StoneSaga_EN.jpg",
    "imageUrlCN": "https://d2bdzvbz2cmjb8.cloudfront.net/epicwin/zh/40047_StoneSaga_CN.jpg",
    "gameID": "40047",
    "gameType": "Slot",
    "rtpRate": "97.08%",
    "hot": false,
    "maintenance": false,
    "createdAt": "2025-10-29T17:34:54.235Z",
    "updatedAt": "2025-10-29T17:34:54.235Z",
    "__v": 0
  },
  {
    "_id": "689224b2c2d97e65ace453f2",
    "gameNameEN": "Uncharted",
    "gameNameCN": "神秘海域",
    "gameNameHK": "神秘海域",
    "imageUrlEN": "https://d2bdzvbz2cmjb8.cloudfront.net/epicwin/en/110036_Uncharted_en.png",
    "imageUrlCN": "https://d2bdzvbz2cmjb8.cloudfront.net/epicwin/zh/110036_Uncharted_cn.png",
    "gameID": "40009",
    "gameType": "Slot",
    "rtpRate": "97.09%",
    "hot": false,
    "maintenance": false,
    "createdAt": "2025-10-29T12:04:54.235Z",
    "updatedAt": "2025-10-29T12:04:54.235Z",
    "__v": 0
  },
  {
    "_id": "689224b2c2d97e65ace4541a",
    "gameNameEN": "Epic 888",
    "gameNameCN": "Epic 888",
    "gameNameHK": "Epic 888",
    "imageUrlEN": "https://d2bdzvbz2cmjb8.cloudfront.net/epicwin/zh/40051_Epic888.png",
    "imageUrlCN": "https://d2bdzvbz2cmjb8.cloudfront.net/epicwin/zh/40051_Epic888.png",
    "gameID": "40051",
    "gameType": "Slot",
    "rtpRate": "96.03%",
    "hot": false,
    "maintenance": false,
    "createdAt": "2025-10-30T12:04:54.235Z",
    "updatedAt": "2025-10-30T12:04:54.235Z",
    "__v": 0
  },
  {
    "_id": "689224b2c2d97e65ace453fa",
    "gameNameEN": "Avatar: The Ways of Water",
    "gameNameCN": "阿凡达：水之道",
    "gameNameHK": "阿凡達：水之道",
    "imageUrlEN": "https://d2bdzvbz2cmjb8.cloudfront.net/epicwin/en/110044_AvatarTheWayofWater_en.png",
    "imageUrlCN": "https://d2bdzvbz2cmjb8.cloudfront.net/epicwin/zh/110044_AvatarTheWayofWater_cn.png",
    "gameID": "40017",
    "gameType": "Slot",
    "rtpRate": "95.81%",
    "hot": false,
    "maintenance": false,
    "createdAt": "2025-10-30T07:34:54.235Z",
    "updatedAt": "2025-10-30T07:34:54.235Z",
    "__v": 0
  },
  {
    "_id": "689224b2c2d97e65ace453fe",
    "gameNameEN": "Riches Of Tiger",
    "gameNameCN": "虎虎生财",
    "gameNameHK": "虎虎生財",
    "imageUrlEN": "https://d2bdzvbz2cmjb8.cloudfront.net/epicwin/en/110047_RichesofTiger_en.png",
    "imageUrlCN": "https://d2bdzvbz2cmjb8.cloudfront.net/epicwin/zh/110047_RichesofTiger_cn.png",
    "gameID": "40021",
    "gameType": "Slot",
    "rtpRate": "96.50%",
    "hot": true,
    "maintenance": false,
    "createdAt": "2025-10-30T01:04:54.235Z",
    "updatedAt": "2025-10-30T01:04:54.235Z",
    "__v": 0
  },
  {
    "_id": "689224b2c2d97e65ace4540e",
    "gameNameEN": "Blue Beetle",
    "gameNameCN": "蓝甲虫",
    "gameNameHK": "藍色甲蟲",
    "imageUrlEN": "https://d2bdzvbz2cmjb8.cloudfront.net/epicwin/en/110063_BlueBeetle_en.png",
    "imageUrlCN": "https://d2bdzvbz2cmjb8.cloudfront.net/epicwin/zh/110063_BlueBeetle_cn.png",
    "gameID": "40037",
    "gameType": "Slot",
    "rtpRate": "96.54%",
    "hot": false,
    "maintenance": false,
    "createdAt": "2025-10-29T10:04:54.235Z",
    "updatedAt": "2025-10-29T10:04:54.235Z",
    "__v": 0
  },
  {
    "_id": "689224b2c2d97e65ace453f6",
    "gameNameEN": "Great Cai Shen",
    "gameNameCN": "大财神",
    "gameNameHK": "大財神",
    "imageUrlEN": "https://d2bdzvbz2cmjb8.cloudfront.net/epicwin/en/110040_GreatCaiShen_en.png",
    "imageUrlCN": "https://d2bdzvbz2cmjb8.cloudfront.net/epicwin/zh/110040_GreatCaiShen_cn.png",
    "gameID": "40013",
    "gameType": "Slot",
    "rtpRate": "97.01%",
    "hot": true,
    "maintenance": false,
    "createdAt": "2025-10-29T22:04:54.235Z",
    "updatedAt": "2025-10-29T22:04:54.235Z",
    "__v": 0
  },
  {
    "_id": "689224b2c2d97e65ace45405",
    "gameNameEN": "Mythical Creatures",
    "gameNameCN": "神兽",
    "gameNameHK": "神獸",
    "imageUrlEN": "https://d2bdzvbz2cmjb8.cloudfront.net/epicwin/en/110054_MythicalCreatures_en.png",
    "imageUrlCN": "https://d2bdzvbz2cmjb8.cloudfront.net/epicwin/zh/110054_MythicalCreatures_cn.png",
    "gameID": "40028",
    "gameType": "Slot",
    "rtpRate": "96.04%",
    "hot": true,
    "maintenance": false,
    "createdAt": "2025-10-29T23:04:54.235Z",
    "updatedAt": "2025-10-29T23:04:54.235Z",
    "__v": 0
  },
  {
    "_id": "689224b2c2d97e65ace45426",
    "gameNameEN": "Bankin' Banker",
    "gameNameCN": "大银行家",
    "gameNameHK": "大銀行家",
    "imageUrlEN": "https://d2bdzvbz2cmjb8.cloudfront.net/epicwin/en/45007_BankinBanker_EN.png",
    "imageUrlCN": "https://d2bdzvbz2cmjb8.cloudfront.net/epicwin/zh/45007_BankinBanker_CN.png",
    "gameID": "45007",
    "gameType": "Slot",
    "rtpRate": "96.00%",
    "hot": false,
    "maintenance": false,
    "createdAt": "2025-10-30T13:34:54.235Z",
    "updatedAt": "2025-10-30T13:34:54.235Z",
    "__v": 0
  },
  {
    "_id": "689224b2c2d97e65ace453ed",
    "gameNameEN": "Born Pink",
    "gameNameCN": "Born Pink",
    "gameNameHK": "Born Pink",
    "imageUrlEN": "https://d2bdzvbz2cmjb8.cloudfront.net/epicwin/en/110031_BornPink_en.png",
    "imageUrlCN": "https://d2bdzvbz2cmjb8.cloudfront.net/epicwin/zh/110031_BornPink_cn.png",
    "gameID": "40003",
    "gameType": "Slot",
    "rtpRate": "97.07%",
    "hot": false,
    "maintenance": false,
    "createdAt": "2025-10-29T16:34:54.235Z",
    "updatedAt": "2025-10-29T16:34:54.235Z",
    "__v": 0
  },
  {
    "_id": "689224b2c2d97e65ace4540d",
    "gameNameEN": "The Secrets of Dumbledore",
    "gameNameCN": "邓不利多的秘密",
    "gameNameHK": "鄧不利多的秘密",
    "imageUrlEN": "https://d2bdzvbz2cmjb8.cloudfront.net/epicwin/en/110062_TheSecretOfDumbledore_en.png",
    "imageUrlCN": "https://d2bdzvbz2cmjb8.cloudfront.net/epicwin/zh/110062_TheSecretOfDumbledore_cn.png",
    "gameID": "40036",
    "gameType": "Slot",
    "rtpRate": "95.41%",
    "hot": false,
    "maintenance": false,
    "createdAt": "2025-10-29T09:34:54.235Z",
    "updatedAt": "2025-10-29T09:34:54.235Z",
    "__v": 0
  },
  {
    "_id": "689224b2c2d97e65ace453eb",
    "gameNameEN": "Nyxus Empress",
    "gameNameCN": "倪克斯女王",
    "gameNameHK": "倪克斯女王",
    "imageUrlEN": "https://d2bdzvbz2cmjb8.cloudfront.net/epicwin/en/110029_NyxusEmpress_en.png",
    "imageUrlCN": "https://d2bdzvbz2cmjb8.cloudfront.net/epicwin/zh/110029_NyxusEmpress_cn.png",
    "gameID": "40001",
    "gameType": "Slot",
    "rtpRate": "97.34%",
    "hot": false,
    "maintenance": false,
    "createdAt": "2025-10-29T14:04:54.235Z",
    "updatedAt": "2025-10-29T14:04:54.235Z",
    "__v": 0
  },
  {
    "_id": "689224b2c2d97e65ace45410",
    "gameNameEN": "Animal Farm",
    "gameNameCN": "动物农场",
    "gameNameHK": "動物農場",
    "imageUrlEN": "https://d2bdzvbz2cmjb8.cloudfront.net/epicwin/en/110067_AnimalFarm_en.png",
    "imageUrlCN": "https://d2bdzvbz2cmjb8.cloudfront.net/epicwin/zh/110067_AnimalFarm_cn.png",
    "gameID": "40039",
    "gameType": "Slot",
    "rtpRate": "96.17%",
    "hot": false,
    "maintenance": false,
    "createdAt": "2025-10-30T01:34:54.235Z",
    "updatedAt": "2025-10-30T01:34:54.235Z",
    "__v": 0
  },
  {
    "_id": "689224b2c2d97e65ace453f8",
    "gameNameEN": "AI City",
    "gameNameCN": "AI 城市",
    "gameNameHK": "AI 城市",
    "imageUrlEN": "https://d2bdzvbz2cmjb8.cloudfront.net/epicwin/en/40015_AiCity_en.png",
    "imageUrlCN": "https://d2bdzvbz2cmjb8.cloudfront.net/epicwin/zh/40015_AiCity_cn.png",
    "gameID": "40015",
    "gameType": "Slot",
    "rtpRate": "95.82%",
    "hot": false,
    "maintenance": false,
    "createdAt": "2025-10-29T10:34:54.235Z",
    "updatedAt": "2025-10-29T10:34:54.235Z",
    "__v": 0
  },
  {
    "_id": "689224b2c2d97e65ace453f9",
    "gameNameEN": "Dragon Saga",
    "gameNameCN": "圣龙传奇",
    "gameNameHK": "聖龍傳奇",
    "imageUrlEN": "https://d2bdzvbz2cmjb8.cloudfront.net/epicwin/en/110043_DragonSaga_en.png",
    "imageUrlCN": "https://d2bdzvbz2cmjb8.cloudfront.net/epicwin/zh/110043_DragonSaga_cn.png",
    "gameID": "40016",
    "gameType": "Slot",
    "rtpRate": "96.45%",
    "hot": false,
    "maintenance": false,
    "createdAt": "2025-10-29T15:34:54.235Z",
    "updatedAt": "2025-10-29T15:34:54.235Z",
    "__v": 0
  },
  {
    "_id": "689224b2c2d97e65ace4540f",
    "gameNameEN": "Moonlight Wish",
    "gameNameCN": "月之心愿",
    "gameNameHK": "月之心願",
    "imageUrlEN": "https://d2bdzvbz2cmjb8.cloudfront.net/epicwin/en/40038_MoonlightWish_en.png",
    "imageUrlCN": "https://d2bdzvbz2cmjb8.cloudfront.net/epicwin/zh/40038_MoonlightWish_cn.png",
    "gameID": "49999",
    "gameType": "Slot",
    "rtpRate": "96.64%",
    "hot": false,
    "maintenance": false,
    "createdAt": "2025-10-29T17:04:54.235Z",
    "updatedAt": "2025-10-29T17:04:54.235Z",
    "__v": 0
  },
  {
    "_id": "689224b2c2d97e65ace45414",
    "gameNameEN": "Epic Ace",
    "gameNameCN": "Epic 扑克A",
    "gameNameHK": "Epic 撲克A",
    "imageUrlEN": "https://d2bdzvbz2cmjb8.cloudfront.net/epicwin/en/40043_EpicAce_EN.jpg",
    "imageUrlCN": "https://d2bdzvbz2cmjb8.cloudfront.net/epicwin/zh/40043_EpicAce_CN.jpg",
    "gameID": "40043",
    "gameType": "Slot",
    "rtpRate": "97.18%",
    "hot": true,
    "maintenance": false,
    "createdAt": "2025-10-30T11:04:54.235Z",
    "updatedAt": "2025-10-30T11:04:54.235Z",
    "__v": 0
  },
  {
    "_id": "689224b2c2d97e65ace45420",
    "gameNameEN": "Avengers: Endgame",
    "gameNameCN": "复仇者联盟：终局之战",
    "gameNameHK": "復仇者聯盟：終局之戰",
    "imageUrlEN": "https://d2bdzvbz2cmjb8.cloudfront.net/epicwin/en/SquareFlatTitle_AvengersEndgame_EN.jpg",
    "imageUrlCN": "https://d2bdzvbz2cmjb8.cloudfront.net/epicwin/zh/SquareFlatTitle_AvengersEndgame_CN.png",
    "gameID": "45003",
    "gameType": "Slot",
    "rtpRate": "96.35%",
    "hot": false,
    "maintenance": false,
    "createdAt": "2025-10-30T03:04:54.235Z",
    "updatedAt": "2025-10-30T03:04:54.235Z",
    "__v": 0
  },
  {
    "_id": "689224b2c2d97e65ace453ff",
    "gameNameEN": "Mulan",
    "gameNameCN": "花木兰",
    "gameNameHK": "花木蘭",
    "imageUrlEN": "https://d2bdzvbz2cmjb8.cloudfront.net/epicwin/en/110048_Mulan_en.png",
    "imageUrlCN": "https://d2bdzvbz2cmjb8.cloudfront.net/epicwin/zh/110048_Mulan_cn.png",
    "gameID": "40022",
    "gameType": "Slot",
    "rtpRate": "97.06%",
    "hot": false,
    "maintenance": false,
    "createdAt": "2025-10-29T22:34:54.235Z",
    "updatedAt": "2025-10-29T22:34:54.235Z",
    "__v": 0
  },
  {
    "_id": "689224b2c2d97e65ace45412",
    "gameNameEN": "God Of The Sun",
    "gameNameCN": "太阳神",
    "gameNameHK": "太陽神",
    "imageUrlEN": "https://d2bdzvbz2cmjb8.cloudfront.net/epicwin/en/110065_GodOfTheSun_en.png",
    "imageUrlCN": "https://d2bdzvbz2cmjb8.cloudfront.net/epicwin/zh/110065_GodOfTheSun_cn.png",
    "gameID": "40041",
    "gameType": "Slot",
    "rtpRate": "97.30%",
    "hot": false,
    "maintenance": false,
    "createdAt": "2025-10-30T00:04:54.235Z",
    "updatedAt": "2025-10-30T00:04:54.235Z",
    "__v": 0
  },
  {
    "_id": "689224b2c2d97e65ace4541e",
    "gameNameEN": "10 CaiShen's Chest",
    "gameNameCN": "财神十宝",
    "gameNameHK": "財神十寶",
    "imageUrlEN": "https://d2bdzvbz2cmjb8.cloudfront.net/epicwin/en/10 CaiShen's Chest_Square_EN.png",
    "imageUrlCN": "https://d2bdzvbz2cmjb8.cloudfront.net/epicwin/zh/10 CaiShen's Chest_Square_CN.png",
    "gameID": "40052",
    "gameType": "Slot",
    "rtpRate": "96.00%",
    "hot": false,
    "maintenance": false,
    "createdAt": "2025-10-30T08:04:54.235Z",
    "updatedAt": "2025-10-30T08:04:54.235Z",
    "__v": 0
  },
  {
    "_id": "689224b2c2d97e65ace45407",
    "gameNameEN": "Epic Highway King",
    "gameNameCN": "Epic 高速公路",
    "gameNameHK": "Epic 高速公路",
    "imageUrlEN": "https://d2bdzvbz2cmjb8.cloudfront.net/epicwin/en/110056_EpicHighwayKings_en.png",
    "imageUrlCN": "https://d2bdzvbz2cmjb8.cloudfront.net/epicwin/zh/110056_EpicHighwayKings_cn.png",
    "gameID": "40030",
    "gameType": "Slot",
    "rtpRate": "96.26%",
    "hot": false,
    "maintenance": false,
    "createdAt": "2025-10-30T02:34:54.235Z",
    "updatedAt": "2025-10-30T02:34:54.235Z",
    "__v": 0
  },
  {
    "_id": "689224b2c2d97e65ace45404",
    "gameNameEN": "Maiden Lotus",
    "gameNameCN": "莲花少女",
    "gameNameHK": "蓮花少女",
    "imageUrlEN": "https://d2bdzvbz2cmjb8.cloudfront.net/epicwin/en/110053_MaidenLotus_en.png",
    "imageUrlCN": "https://d2bdzvbz2cmjb8.cloudfront.net/epicwin/zh/110053_MaidenLotus_cn.png",
    "gameID": "40027",
    "gameType": "Slot",
    "rtpRate": "96.52%",
    "hot": false,
    "maintenance": false,
    "createdAt": "2025-10-29T13:34:54.235Z",
    "updatedAt": "2025-10-29T13:34:54.235Z",
    "__v": 0
  },
  {
    "_id": "689224b2c2d97e65ace453fc",
    "gameNameEN": "Let's Party EpicWays",
    "gameNameCN": "狂欢派对 EpicWays",
    "gameNameHK": "狂歡派對 EpicWays",
    "imageUrlEN": "https://d2bdzvbz2cmjb8.cloudfront.net/epicwin/en/40019_LetsPartyEpicways_en.png",
    "imageUrlCN": "https://d2bdzvbz2cmjb8.cloudfront.net/epicwin/zh/40019_LetsPartyEpicways_cn.png",
    "gameID": "40019",
    "gameType": "Slot",
    "rtpRate": "96.35%",
    "hot": false,
    "maintenance": false,
    "createdAt": "2025-10-29T15:04:54.235Z",
    "updatedAt": "2025-10-29T15:04:54.235Z",
    "__v": 0
  },
  {
    "_id": "689224b2c2d97e65ace45417",
    "gameNameEN": "Master Of The Sun",
    "gameNameCN": "阳光之主",
    "gameNameHK": "陽光之主",
    "imageUrlEN": "https://d2bdzvbz2cmjb8.cloudfront.net/epicwin/en/40046_MasterOfTheSun_EN.jpg",
    "imageUrlCN": "https://d2bdzvbz2cmjb8.cloudfront.net/epicwin/zh/40046_MasterOfTheSun_CN.jpg",
    "gameID": "40046",
    "gameType": "Slot",
    "rtpRate": "96.92%",
    "hot": true,
    "maintenance": false,
    "createdAt": "2025-10-30T02:04:54.235Z",
    "updatedAt": "2025-10-30T02:04:54.235Z",
    "__v": 0
  },
  {
    "_id": "689224b2c2d97e65ace4541f",
    "gameNameEN": "Street Mania Deluxe",
    "gameNameCN": "豪华街头狂热",
    "gameNameHK": "豪華街頭狂熱",
    "imageUrlEN": "https://d2bdzvbz2cmjb8.cloudfront.net/epicwin/en/StreetManiaDeluxe_EN.png",
    "imageUrlCN": "https://d2bdzvbz2cmjb8.cloudfront.net/epicwin/zh/StreetManiaDeluxe_CN.png",
    "gameID": "49997",
    "gameType": "Slot",
    "rtpRate": "96.08%",
    "hot": false,
    "maintenance": false,
    "createdAt": "2025-10-30T03:34:54.235Z",
    "updatedAt": "2025-10-30T03:34:54.235Z",
    "__v": 0
  },
  {
    "_id": "689224b2c2d97e65ace453f4",
    "gameNameEN": "Epic Panther Moon",
    "gameNameCN": "Epic 黑豹之月",
    "gameNameHK": "Epic 黑豹之月",
    "imageUrlEN": "https://d2bdzvbz2cmjb8.cloudfront.net/epicwin/en/110038_PantherMoon_en.png",
    "imageUrlCN": "https://d2bdzvbz2cmjb8.cloudfront.net/epicwin/zh/110038_PantherMoon_cn.png",
    "gameID": "40011",
    "gameType": "Slot",
    "rtpRate": "96.46%",
    "hot": true,
    "maintenance": false,
    "createdAt": "2025-10-30T04:04:54.235Z",
    "updatedAt": "2025-10-30T04:04:54.235Z",
    "__v": 0
  },
  {
    "_id": "689224b2c2d97e65ace45421",
    "gameNameEN": "Aztec Riches",
    "gameNameCN": "阿茲特之富",
    "gameNameHK": "阿茲特之富",
    "imageUrlEN": "https://d2bdzvbz2cmjb8.cloudfront.net/epicwin/en/40053_AztecRiches_EN.jpg",
    "imageUrlCN": "https://d2bdzvbz2cmjb8.cloudfront.net/epicwin/zh/40053_AztecRiches_CN.jpg",
    "gameID": "40053",
    "gameType": "Slot",
    "rtpRate": "96.00%",
    "hot": false,
    "maintenance": false,
    "createdAt": "2025-10-30T09:34:54.235Z",
    "updatedAt": "2025-10-30T09:34:54.235Z",
    "__v": 0
  },
  {
    "_id": "689224b2c2d97e65ace45406",
    "gameNameEN": "Spring Tails",
    "gameNameCN": "春天物语",
    "gameNameHK": "春天物語",
    "imageUrlEN": "https://d2bdzvbz2cmjb8.cloudfront.net/epicwin/en/110055_SpringTails_en.png",
    "imageUrlCN": "https://d2bdzvbz2cmjb8.cloudfront.net/epicwin/zh/110055_SpringTails_cn.png",
    "gameID": "40029",
    "gameType": "Slot",
    "rtpRate": "96.48%",
    "hot": false,
    "maintenance": false,
    "createdAt": "2025-10-29T19:34:54.235Z",
    "updatedAt": "2025-10-29T19:34:54.235Z",
    "__v": 0
  },
  {
    "_id": "689224b2c2d97e65ace4540c",
    "gameNameEN": "Jurassic World Dominion",
    "gameNameCN": "侏罗纪世界：统霸天下",
    "gameNameHK": "侏羅紀世界：統霸天下",
    "imageUrlEN": "https://d2bdzvbz2cmjb8.cloudfront.net/epicwin/en/110061_Jurassic-WorldDominion_en.png",
    "imageUrlCN": "https://d2bdzvbz2cmjb8.cloudfront.net/epicwin/zh/110061_Jurassic-WorldDominion_cn.png",
    "gameID": "40035",
    "gameType": "Slot",
    "rtpRate": "95.05%",
    "hot": false,
    "maintenance": false,
    "createdAt": "2025-10-29T08:04:54.235Z",
    "updatedAt": "2025-10-29T08:04:54.235Z",
    "__v": 0
  },
  {
    "_id": "689224b2c2d97e65ace453fd",
    "gameNameEN": "Royal Heart",
    "gameNameCN": "皇家之心",
    "gameNameHK": "皇家之心",
    "imageUrlEN": "https://d2bdzvbz2cmjb8.cloudfront.net/epicwin/en/40020_RoyalHeart_en.png",
    "imageUrlCN": "https://d2bdzvbz2cmjb8.cloudfront.net/epicwin/zh/40020_RoyalHeart_cn.png",
    "gameID": "40020",
    "gameType": "Slot",
    "rtpRate": "96.84%",
    "hot": false,
    "maintenance": false,
    "createdAt": "2025-10-29T21:04:54.235Z",
    "updatedAt": "2025-10-29T21:04:54.235Z",
    "__v": 0
  },
  {
    "_id": "689224b2c2d97e65ace453ea",
    "gameNameEN": "Book Of Genie",
    "gameNameCN": "精灵之书",
    "gameNameHK": "精靈之書",
    "imageUrlEN": "https://d2bdzvbz2cmjb8.cloudfront.net/epicwin/en/110028_BookOfGenie_en.png",
    "imageUrlCN": "https://d2bdzvbz2cmjb8.cloudfront.net/epicwin/zh/110028_BookOfGenie_cn.png",
    "gameID": "40000",
    "gameType": "Slot",
    "rtpRate": "96.84%",
    "hot": false,
    "maintenance": false,
    "createdAt": "2025-10-30T12:34:54.235Z",
    "updatedAt": "2025-10-30T12:34:54.235Z",
    "__v": 0
  },
  {
    "_id": "68b018da02fe26a0766f21fb",
    "gameNameEN": "Epic Lamp",
    "gameNameCN": "Epic神灯",
    "gameNameHK": "Epic神燈",
    "imageUrlEN": "https://d2bdzvbz2cmjb8.cloudfront.net/epicwin/en/45008_Epic+Lamp_640x640_EN.jpg",
    "imageUrlCN": "https://d2bdzvbz2cmjb8.cloudfront.net/epicwin/zh/45008_Epic+Lamp_640x640_CN.jpg",
    "gameID": "45008",
    "gameType": "Slot",
    "rtpRate": "96.00%",
    "hot": false,
    "maintenance": false,
    "createdAt": "2025-10-30T14:34:54.235Z",
    "updatedAt": "2025-10-30T14:34:54.235Z",
    "__v": 0
  },
  {
    "_id": "689224b2c2d97e65ace453f0",
    "gameNameEN": "Imperial Diamond",
    "gameNameCN": "帝国钻石",
    "gameNameHK": "帝國鑽石",
    "imageUrlEN": "https://d2bdzvbz2cmjb8.cloudfront.net/epicwin/en/110067_ImperialDiamonds_en.png",
    "imageUrlCN": "https://d2bdzvbz2cmjb8.cloudfront.net/epicwin/zh/110067_ImperialDiamonds_cn.png",
    "gameID": "40007",
    "gameType": "Slot",
    "rtpRate": "96.18%",
    "hot": true,
    "maintenance": false,
    "createdAt": "2025-10-30T06:34:54.235Z",
    "updatedAt": "2025-10-30T06:34:54.235Z",
    "__v": 0
  },
  {
    "_id": "689224b2c2d97e65ace45409",
    "gameNameEN": "Thor Love and Thunder",
    "gameNameCN": "雷神：爱与雷霆",
    "gameNameHK": "雷神：愛與雷霆",
    "imageUrlEN": "https://d2bdzvbz2cmjb8.cloudfront.net/epicwin/en/110058_ThorLoveandThunder_en.png",
    "imageUrlCN": "https://d2bdzvbz2cmjb8.cloudfront.net/epicwin/zh/110058_ThorLoveandThunder_cn.png",
    "gameID": "40032",
    "gameType": "Slot",
    "rtpRate": "96.85%",
    "hot": false,
    "maintenance": false,
    "createdAt": "2025-10-29T11:34:54.235Z",
    "updatedAt": "2025-10-29T11:34:54.235Z",
    "__v": 0
  },
  {
    "_id": "689224b2c2d97e65ace4540a",
    "gameNameEN": "Jungle Cruise",
    "gameNameCN": "丛林奇航",
    "gameNameHK": "叢林奇航",
    "imageUrlEN": "https://d2bdzvbz2cmjb8.cloudfront.net/epicwin/en/110059_JungleCruise_en.png",
    "imageUrlCN": "https://d2bdzvbz2cmjb8.cloudfront.net/epicwin/zh/110059_JungleCruise_cn.png",
    "gameID": "40033",
    "gameType": "Slot",
    "rtpRate": "95.69%",
    "hot": false,
    "maintenance": false,
    "createdAt": "2025-10-29T09:04:54.235Z",
    "updatedAt": "2025-10-29T09:04:54.235Z",
    "__v": 0
  },
  {
    "_id": "689224b2c2d97e65ace45416",
    "gameNameEN": "Godzilla VS Kong",
    "gameNameCN": "哥斯拉大战金刚",
    "gameNameHK": "哥吉拉大戰金剛",
    "imageUrlEN": "https://d2bdzvbz2cmjb8.cloudfront.net/epicwin/en/40048_GodzillaVCKong.png",
    "imageUrlCN": "https://d2bdzvbz2cmjb8.cloudfront.net/epicwin/zh/40048_GodzillaVCKong.png",
    "gameID": "40048",
    "gameType": "Slot",
    "rtpRate": "97.12%",
    "hot": false,
    "maintenance": false,
    "createdAt": "2025-10-29T12:34:54.235Z",
    "updatedAt": "2025-10-29T12:34:54.235Z",
    "__v": 0
  },
  {
    "_id": "689224b2c2d97e65ace45425",
    "gameNameEN": "Slot4D",
    "gameNameCN": "Slot4D",
    "gameNameHK": "Slot4D",
    "gameID": "48001",
    "gameType": "Slot",
    "rtpRate": "96.50%",
    "hot": false,
    "maintenance": true,
    "createdAt": "2025-08-27T19:27:16.032Z",
    "updatedAt": "2025-10-30T14:58:59.602Z",
    "__v": 0
  },
  {
    "_id": "689224b2c2d97e65ace4541c",
    "gameNameEN": "5 Wukong",
    "gameNameCN": "五灵悟空",
    "gameNameHK": "五靈悟空",
    "imageUrlEN": "https://d2bdzvbz2cmjb8.cloudfront.net/epicwin/en/Square_450020_5Wukong_EN.jpg",
    "imageUrlCN": "https://d2bdzvbz2cmjb8.cloudfront.net/epicwin/zh/Square_450020_5Wukong_CN.jpg",
    "gameID": "45002",
    "gameType": "Slot",
    "rtpRate": "96.00%",
    "hot": false,
    "maintenance": false,
    "createdAt": "2025-10-30T04:34:54.235Z",
    "updatedAt": "2025-10-30T04:34:54.235Z",
    "__v": 0
  },
  {
    "_id": "689224b2c2d97e65ace453ec",
    "gameNameEN": "Great Prosperity",
    "gameNameCN": "至高财富",
    "gameNameHK": "至高財富",
    "imageUrlEN": "https://d2bdzvbz2cmjb8.cloudfront.net/epicwin/en/110030_GreatProsperity_en.png",
    "imageUrlCN": "https://d2bdzvbz2cmjb8.cloudfront.net/epicwin/zh/110030_GreatProsperity_cn.png",
    "gameID": "40002",
    "gameType": "Slot",
    "rtpRate": "96.83%",
    "hot": true,
    "maintenance": false,
    "createdAt": "2025-10-30T06:04:54.235Z",
    "updatedAt": "2025-10-30T06:04:54.235Z",
    "__v": 0
  },
  {
    "_id": "689224b2c2d97e65ace45418",
    "gameNameEN": "Streetball League",
    "gameNameCN": "街球之霸",
    "gameNameHK": "街球之霸",
    "imageUrlEN": "https://d2bdzvbz2cmjb8.cloudfront.net/epicwin/en/40049_StreetballLeague_EN.jpg",
    "imageUrlCN": "https://d2bdzvbz2cmjb8.cloudfront.net/epicwin/zh/40049_StreetballLeague_CN.jpg",
    "gameID": "40049",
    "gameType": "Slot",
    "rtpRate": "97.04%",
    "hot": false,
    "maintenance": false,
    "createdAt": "2025-10-29T13:04:54.235Z",
    "updatedAt": "2025-10-29T13:04:54.235Z",
    "__v": 0
  },
  {
    "_id": "689224b2c2d97e65ace45401",
    "gameNameEN": "The Great Monkey",
    "gameNameCN": "齐天大圣",
    "gameNameHK": "齊天大聖",
    "imageUrlEN": "https://d2bdzvbz2cmjb8.cloudfront.net/epicwin/en/110050_TheGreatMonkey_en.png",
    "imageUrlCN": "https://d2bdzvbz2cmjb8.cloudfront.net/epicwin/zh/110050_TheGreatMonkey_cn.png",
    "gameID": "40024",
    "gameType": "Slot",
    "rtpRate": "96.68%",
    "hot": false,
    "maintenance": false,
    "createdAt": "2025-10-29T21:34:54.235Z",
    "updatedAt": "2025-10-29T21:34:54.235Z",
    "__v": 0
  },
  {
    "_id": "689224b2c2d97e65ace45411",
    "gameNameEN": "Dark Angel",
    "gameNameCN": "暗之天使",
    "gameNameHK": "暗之天使",
    "imageUrlEN": "https://d2bdzvbz2cmjb8.cloudfront.net/epicwin/en/40040_DarkAngel_en.png",
    "imageUrlCN": "https://d2bdzvbz2cmjb8.cloudfront.net/epicwin/zh/40040_DarkAngel_cn.png",
    "gameID": "49998",
    "gameType": "Slot",
    "rtpRate": "97.06%",
    "hot": false,
    "maintenance": false,
    "createdAt": "2025-10-29T20:34:54.235Z",
    "updatedAt": "2025-10-29T20:34:54.235Z",
    "__v": 0
  },
  {
    "_id": "689224b2c2d97e65ace45419",
    "gameNameEN": "Lucy",
    "gameNameCN": "露西",
    "gameNameHK": "露西",
    "imageUrlEN": "https://d2bdzvbz2cmjb8.cloudfront.net/epicwin/en/40050_Lucy_EN.png",
    "imageUrlCN": "https://d2bdzvbz2cmjb8.cloudfront.net/epicwin/zh/40050_Lucy_CN.png",
    "gameID": "40050",
    "gameType": "Slot",
    "rtpRate": "97.08%",
    "hot": false,
    "maintenance": false,
    "createdAt": "2025-10-29T18:34:54.235Z",
    "updatedAt": "2025-10-29T18:34:54.235Z",
    "__v": 0
  },
  {
    "_id": "689224b2c2d97e65ace453f1",
    "gameNameEN": "Crystal Mage",
    "gameNameCN": "水晶法师",
    "gameNameHK": "水晶法師",
    "imageUrlEN": "https://d2bdzvbz2cmjb8.cloudfront.net/epicwin/en/110035_CrystalMage_en.png",
    "imageUrlCN": "https://d2bdzvbz2cmjb8.cloudfront.net/epicwin/zh/110035_CrystalMage_cn.png",
    "gameID": "40008",
    "gameType": "Slot",
    "rtpRate": "96.84%",
    "hot": false,
    "maintenance": false,
    "createdAt": "2025-10-29T14:34:54.235Z",
    "updatedAt": "2025-10-29T14:34:54.235Z",
    "__v": 0
  },
  {
    "_id": "689224b2c2d97e65ace453fb",
    "gameNameEN": "Lucky Champion",
    "gameNameCN": "幸运冠军",
    "gameNameHK": "幸運冠軍",
    "imageUrlEN": "https://d2bdzvbz2cmjb8.cloudfront.net/epicwin/en/110045_LuckyChampion_en.png",
    "imageUrlCN": "https://d2bdzvbz2cmjb8.cloudfront.net/epicwin/zh/110045_LuckyChampion_cn.png",
    "gameID": "40018",
    "gameType": "Slot",
    "rtpRate": "96.43%",
    "hot": false,
    "maintenance": false,
    "createdAt": "2025-10-29T16:04:54.235Z",
    "updatedAt": "2025-10-29T16:04:54.235Z",
    "__v": 0
  },
  {
    "_id": "689224b2c2d97e65ace4541b",
    "gameNameEN": "Epic Ace Deluxe",
    "gameNameCN": "Epic 豪华扑克A",
    "gameNameHK": "Epic 豪華撲克A",
    "imageUrlEN": "https://d2bdzvbz2cmjb8.cloudfront.net/epicwin/en/Square_45000_Epic-Ace-Deluxe_EN.png",
    "imageUrlCN": "https://d2bdzvbz2cmjb8.cloudfront.net/epicwin/zh/Square_45000_Epic-Ace-Deluxe_CN.png",
    "gameID": "45000",
    "gameType": "Slot",
    "rtpRate": "96.30%",
    "hot": false,
    "maintenance": false,
    "createdAt": "2025-10-30T10:34:54.235Z",
    "updatedAt": "2025-10-30T10:34:54.235Z",
    "__v": 0
  },
  {
    "_id": "68ea021711d64a95028b3800",
    "gameNameEN": "QianZhuang Legend",
    "gameNameCN": "钱庄传说",
    "gameNameHK": "錢莊傳說",
    "imageUrlEN": "https://d2bdzvbz2cmjb8.cloudfront.net/epicwin/en/Thumbnail-Qian-Zhuang-Legend-500-x-500.png",
    "imageUrlCN": "https://d2bdzvbz2cmjb8.cloudfront.net/epicwin/zh/Thumbnail-Qian-Zhuang-Legend-500-x-500-2.png",
    "gameID": "40054",
    "gameType": "Slot",
    "rtpRate": "96.50%",
    "hot": false,
    "maintenance": false,
    "createdAt": "2025-10-30T14:04:54.235Z",
    "updatedAt": "2025-10-30T14:04:54.235Z",
    "__v": 0
  },
  {
    "_id": "689224b2c2d97e65ace453ee",
    "gameNameEN": "S.T.U.N.",
    "gameNameCN": "S.T.U.N.",
    "gameNameHK": "S.T.U.N.",
    "imageUrlEN": "https://d2bdzvbz2cmjb8.cloudfront.net/epicwin/en/110032_STUN_en.png",
    "imageUrlCN": "https://d2bdzvbz2cmjb8.cloudfront.net/epicwin/zh/110032_STUN_cn.png",
    "gameID": "40004",
    "gameType": "Slot",
    "rtpRate": "96.71%",
    "hot": false,
    "maintenance": false,
    "createdAt": "2025-10-29T19:04:54.235Z",
    "updatedAt": "2025-10-29T19:04:54.235Z",
    "__v": 0
  },
  {
    "_id": "689224b2c2d97e65ace453f7",
    "gameNameEN": "Ninja Evolution",
    "gameNameCN": "忍者进化",
    "gameNameHK": "忍者進化",
    "imageUrlEN": "https://d2bdzvbz2cmjb8.cloudfront.net/epicwin/en/110041_NinjaEvolution_en.png",
    "imageUrlCN": "https://d2bdzvbz2cmjb8.cloudfront.net/epicwin/zh/110041_NinjaEvolution_cn.png",
    "gameID": "40014",
    "gameType": "Slot",
    "rtpRate": "96.27%",
    "hot": true,
    "maintenance": false,
    "createdAt": "2025-10-30T05:34:54.235Z",
    "updatedAt": "2025-10-30T05:34:54.235Z",
    "__v": 0
  },
  {
    "_id": "689224b2c2d97e65ace45422",
    "gameNameEN": "Money Bang Bang",
    "gameNameCN": "财运棒棒",
    "gameNameHK": "財運棒",
    "imageUrlEN": "https://d2bdzvbz2cmjb8.cloudfront.net/epicwin/en/Square_Money Bang Bang_EN.jpg",
    "imageUrlCN": "https://d2bdzvbz2cmjb8.cloudfront.net/epicwin/zh/Square_Money Bang Bang_CN.jpg",
    "gameID": "45004",
    "gameType": "Slot",
    "rtpRate": "96.00%",
    "hot": false,
    "maintenance": false,
    "createdAt": "2025-10-30T07:04:54.235Z",
    "updatedAt": "2025-10-30T07:04:54.235Z",
    "__v": 0
  },
  {
    "_id": "689224b2c2d97e65ace45408",
    "gameNameEN": "Year Of The Ox",
    "gameNameCN": "牛年",
    "gameNameHK": "牛年",
    "imageUrlEN": "https://d2bdzvbz2cmjb8.cloudfront.net/epicwin/en/110057_YearOfTheOx_en.png",
    "imageUrlCN": "https://d2bdzvbz2cmjb8.cloudfront.net/epicwin/zh/110057_YearOfTheOx_cn.png",
    "gameID": "40031",
    "gameType": "Slot",
    "rtpRate": "95.86%",
    "hot": false,
    "maintenance": false,
    "createdAt": "2025-10-29T18:04:54.235Z",
    "updatedAt": "2025-10-29T18:04:54.235Z",
    "__v": 0
  }
]